decawave_ble/__init__.py
decawave_ble/configure_devices.py
decawave_ble/config/__init__.py
decawave_ble/config/csv.py
decawave_ble/config/csvs3.py
decawave_ble-0.9.7.dist-info/LICENSE
decawave_ble-0.9.7.dist-info/METADATA
decawave_ble-0.9.7.dist-info/WHEEL
decawave_ble-0.9.7.dist-info/top_level.txt
decawave_ble-0.9.7.dist-info/RECORD
