Metadata-Version: 2.1
Name: decawave-ble
Version: 0.9.7
Summary: Python toolset for working with and configuring the Decawave DWM1000 devices
Home-page: https://github.com/WildflowerSchools/decawave_ble
Author: tcquinn
Author-email: tcquinn@wildflowerschools.org
License: UNKNOWN
Keywords: bluetooth
Platform: UNKNOWN
Classifier: Intended Audience :: Developers
Classifier: License :: OSI Approved :: MIT License
Classifier: Operating System :: OS Independent
Classifier: Programming Language :: Python
Requires-Dist: bluepy
Requires-Dist: tenacity
Requires-Dist: bitstruct
Provides-Extra: csv
Requires-Dist: pandas ; extra == 'csv'
Requires-Dist: numpy ; extra == 'csv'
Provides-Extra: s3
Requires-Dist: boto3 ; extra == 's3'
